luminos
plugins
